LICENSE
MANIFEST.in
README.md
client.py
requirements
setup.py
mmirman/__init__.py
mmirman/conpig.py
word/__init__.py
word/grapher.py
wordgrapher.egg-info/PKG-INFO
wordgrapher.egg-info/SOURCES.txt
wordgrapher.egg-info/dependency_links.txt
wordgrapher.egg-info/top_level.txt