Metadata-Version: 1.0
Name: wordgrapher
Version: 0.3.0
Summary: Word Graph utility built with NLTK and TextBlob
Home-page: https://github.com/tistaharahap/WordGraph
Author: Batista Harahap
Author-email: batista@bango29.com
License: The MIT License (MIT)
